cyberlicensing/__init__.py
cyberlicensing/client.py
cyberlicensing/environment.py
cyberlicensing/exceptions.py
cyberlicensing/manager.py
cyberlicensing-0.3.0.dist-info/METADATA
cyberlicensing-0.3.0.dist-info/WHEEL
cyberlicensing-0.3.0.dist-info/top_level.txt
cyberlicensing-0.3.0.dist-info/RECORD
