Metadata-Version: 2.4
Name: cyberlicensing
Version: 0.3.0
Summary: Client and manager helpers for CyberLicensing
Author-email: CyberLicensing <me@showdown.boo>
Project-URL: Homepage, https://licensing.showdown.boo/
Requires-Python: >=3.9
Requires-Dist: requests>=2.31.0
